[{"condition": "全天 - 晴天", "data": [{"name": "Magmar", "alpha": false, "%": 61.41, "level": "31 - 34"}, {"name": "Graveler", "alpha": false, "%": 30.71, "level": "31 - 34"}, {"name": "Magby", "alpha": false, "%": 6.14, "level": "26 - 29"}, {"name": "Magmar", "alpha": true, "%": 0.61, "level": "46 - 49"}, {"name": "Magby", "alpha": true, "%": 0.61, "level": "41 - 44"}, {"name": "Graveler", "alpha": true, "%": 0.51, "level": "46 - 49"}]}, {"condition": "全天 - 多雲", "data": [{"name": "Graveler", "alpha": false, "%": 51.28, "level": "31 - 34"}, {"name": "Magmar", "alpha": false, "%": 42.74, "level": "31 - 34"}, {"name": "Magby", "alpha": false, "%": 4.27, "level": "26 - 29"}, {"name": "Graveler", "alpha": true, "%": 0.85, "level": "46 - 49"}, {"name": "Magmar", "alpha": true, "%": 0.43, "level": "46 - 49"}, {"name": "Magby", "alpha": true, "%": 0.43, "level": "41 - 44"}]}, {"condition": "全天 - 雨天", "data": [{"name": "Graveler", "alpha": false, "%": 51.28, "level": "31 - 34"}, {"name": "Magmar", "alpha": false, "%": 42.74, "level": "31 - 34"}, {"name": "Magby", "alpha": false, "%": 4.27, "level": "26 - 29"}, {"name": "Graveler", "alpha": true, "%": 0.85, "level": "46 - 49"}, {"name": "Magmar", "alpha": true, "%": 0.43, "level": "46 - 49"}, {"name": "Magby", "alpha": true, "%": 0.43, "level": "41 - 44"}]}, {"condition": "全天 - 下雪", "data": [{"name": "Graveler", "alpha": false, "%": 51.28, "level": "31 - 34"}, {"name": "Magmar", "alpha": false, "%": 42.74, "level": "31 - 34"}, {"name": "Magby", "alpha": false, "%": 4.27, "level": "26 - 29"}, {"name": "Graveler", "alpha": true, "%": 0.85, "level": "46 - 49"}, {"name": "Magmar", "alpha": true, "%": 0.43, "level": "46 - 49"}, {"name": "Magby", "alpha": true, "%": 0.43, "level": "41 - 44"}]}, {"condition": "全天 - 乾旱", "data": [{"name": "Magmar", "alpha": false, "%": 65.5, "level": "31 - 34"}, {"name": "Graveler", "alpha": false, "%": 26.2, "level": "31 - 34"}, {"name": "Magby", "alpha": false, "%": 6.55, "level": "26 - 29"}, {"name": "Magmar", "alpha": true, "%": 0.66, "level": "46 - 49"}, {"name": "Magby", "alpha": true, "%": 0.66, "level": "41 - 44"}, {"name": "Graveler", "alpha": true, "%": 0.44, "level": "46 - 49"}]}, {"condition": "全天 - 起霧", "data": [{"name": "Graveler", "alpha": false, "%": 51.28, "level": "31 - 34"}, {"name": "Magmar", "alpha": false, "%": 42.74, "level": "31 - 34"}, {"name": "Magby", "alpha": false, "%": 4.27, "level": "26 - 29"}, {"name": "Graveler", "alpha": true, "%": 0.85, "level": "46 - 49"}, {"name": "Magmar", "alpha": true, "%": 0.43, "level": "46 - 49"}, {"name": "Magby", "alpha": true, "%": 0.43, "level": "41 - 44"}]}, {"condition": "全天 - 暴雨", "data": [{"name": "Graveler", "alpha": false, "%": 51.28, "level": "31 - 34"}, {"name": "Magmar", "alpha": false, "%": 42.74, "level": "31 - 34"}, {"name": "Magby", "alpha": false, "%": 4.27, "level": "26 - 29"}, {"name": "Graveler", "alpha": true, "%": 0.85, "level": "46 - 49"}, {"name": "Magmar", "alpha": true, "%": 0.43, "level": "46 - 49"}, {"name": "Magby", "alpha": true, "%": 0.43, "level": "41 - 44"}]}, {"condition": "全天 - 暴風雪", "data": [{"name": "Graveler", "alpha": false, "%": 51.28, "level": "31 - 34"}, {"name": "Magmar", "alpha": false, "%": 42.74, "level": "31 - 34"}, {"name": "Magby", "alpha": false, "%": 4.27, "level": "26 - 29"}, {"name": "Graveler", "alpha": true, "%": 0.85, "level": "46 - 49"}, {"name": "Magmar", "alpha": true, "%": 0.43, "level": "46 - 49"}, {"name": "Magby", "alpha": true, "%": 0.43, "level": "41 - 44"}]}]